pymoose_development_jayesh.libs/libgslcblas-cd2c2030.so.0.0.0
pymoose_development_jayesh.libs/libgsl-b64c76bc.so.23.1.0
rdesigneur/rdesigneurProtos.py
rdesigneur/.gitignore
rdesigneur/rmoogli.py
rdesigneur/__init__.py
rdesigneur/nsdfview.py
rdesigneur/moogul.py
rdesigneur/rdesigneur.py
rdesigneur/cells/DHC-neuron.CNG.swc
rdesigneur/cells/CA1.morph.xml
rdesigneur/cells/ca1_minimal.p
rdesigneur/cells/970529c.CNG.swc
rdesigneur/cells/barrionuevo_cell1zr.CNG.swc
rdesigneur/cells/VHC-neuron.CNG.swc
rdesigneur/cells/h10.CNG.swc
rdesigneur/chans/kdr.xml
rdesigneur/chans/NMDA.xml
rdesigneur/chans/pas.xml
rdesigneur/chans/kad.xml
rdesigneur/chans/kap.xml
rdesigneur/chans/Ca.xml
rdesigneur/chans/CA1.morph.xml
rdesigneur/chans/Generated.net.xml
rdesigneur/chans/hd.xml
rdesigneur/chans/na3.xml
rdesigneur/chans/HChannel.xml
rdesigneur/chans/Glu.xml
rdesigneur/chans/DoubExpSyn.xml
rdesigneur/chans/CaConc.xml
rdesigneur/chans/nax.xml
moose/network_utils.py
moose/constants.py
moose/methods_utils.py
moose/fixXreacs.py
moose/moose_constants.py
moose/streamer_utils.py
moose/moose_legacy.py
moose/hdfutil.py
moose/utils.py
moose/tests.py
moose/helper.py
moose/_moose.cpython-38-x86_64-linux-gnu.so
moose/__init__.py
moose/optimizer_interface.py
moose/print_utils.py
moose/server.py
moose/model_utils.py
moose/recording.py
moose/plot_utils.py
moose/neuroml/NeuroML.py
moose/neuroml/MorphML.py
moose/neuroml/NetworkML.py
moose/neuroml/utils.py
moose/neuroml/__init__.py
moose/neuroml/ChannelML.py
moose/neuroml2/test_reader4.py
moose/neuroml2/test_reader3.py
moose/neuroml2/run_hhcell.py
moose/neuroml2/reader.py
moose/neuroml2/run_cell.py
moose/neuroml2/units.py
moose/neuroml2/test_reader.py
moose/neuroml2/__init__.py
moose/neuroml2/test_reader2.py
moose/neuroml2/README
moose/neuroml2/hhfit.py
moose/neuroml2/test_granule98.py
moose/neuroml2/schema/NeuroMLCoreDimensions.xml
moose/neuroml2/test_files/LEMS_passiveCell.xml
pymoose_development_jayesh-4.1.2.dist-info/LICENSE
pymoose_development_jayesh-4.1.2.dist-info/WHEEL
pymoose_development_jayesh-4.1.2.dist-info/RECORD
pymoose_development_jayesh-4.1.2.dist-info/METADATA
